AUTHORS
COPYING
COPYING.LESSER
ChangeLog
INSTALL
MANIFEST.in
README.md
pyproject.toml
setup.cfg
setup.py
doc/conf.py
doc/efl.rst
doc/index.rst
doc/dbus/dbus.rst
doc/ecore/class-animator.rst
doc/ecore/class-animator_timeline.rst
doc/ecore/class-exe.rst
doc/ecore/class-fdhandler.rst
doc/ecore/class-filedownload.rst
doc/ecore/class-filemonitor.rst
doc/ecore/class-idleenterer.rst
doc/ecore/class-idleexiter.rst
doc/ecore/class-idler.rst
doc/ecore/class-lookup.rst
doc/ecore/class-poller.rst
doc/ecore/class-timer.rst
doc/ecore/class-url.rst
doc/ecore/ecore.rst
doc/ecore/module-ecore.rst
doc/ecore/module-ecore_con.rst
doc/ecore/module-ecore_input.rst
doc/edje/class-edje.rst
doc/edje/edje.rst
doc/edje/module-edje.rst
doc/elementary/actionslider.rst
doc/elementary/background.rst
doc/elementary/box.rst
doc/elementary/bubble.rst
doc/elementary/button.rst
doc/elementary/calendar.rst
doc/elementary/check.rst
doc/elementary/clock.rst
doc/elementary/colorselector.rst
doc/elementary/combobox.rst
doc/elementary/configuration.rst
doc/elementary/conformant.rst
doc/elementary/ctxpopup.rst
doc/elementary/datetime.rst
doc/elementary/dayselector.rst
doc/elementary/diskselector.rst
doc/elementary/elementary.rst
doc/elementary/entry.rst
doc/elementary/fileselector.rst
doc/elementary/fileselector_button.rst
doc/elementary/fileselector_entry.rst
doc/elementary/flip.rst
doc/elementary/flipselector.rst
doc/elementary/frame.rst
doc/elementary/gengrid.rst
doc/elementary/genlist.rst
doc/elementary/gesture_layer.rst
doc/elementary/grid.rst
doc/elementary/hover.rst
doc/elementary/hoversel.rst
doc/elementary/icon.rst
doc/elementary/image.rst
doc/elementary/index.rst
doc/elementary/innerwindow.rst
doc/elementary/label.rst
doc/elementary/layout.rst
doc/elementary/list.rst
doc/elementary/map.rst
doc/elementary/mapbuf.rst
doc/elementary/menu.rst
doc/elementary/multibuttonentry.rst
doc/elementary/naviframe.rst
doc/elementary/need.rst
doc/elementary/notify.rst
doc/elementary/object.rst
python_efl.egg-info/PKG-INFO
python_efl.egg-info/SOURCES.txt
python_efl.egg-info/dependency_links.txt
python_efl.egg-info/not-zip-safe
python_efl.egg-info/top_level.txt
