Metadata-Version: 2.1
Name: python-efl
Version: 1.26.0
Summary: Python bindings for Enlightenment Foundation Libraries
Home-page: http://www.enlightenment.org
Author: Davide Andreoli, Kai Huuhko, and others
Author-email: dave@gurumeditation.it, kai.huuhko@gmail.com
License: GNU Lesser General Public License (LGPL)
Keywords: efl wrapper binding enlightenment eo evas ecore edje emotion elementary ethumb
Platform: UNKNOWN
Classifier: Development Status :: 5 - Production/Stable
Classifier: Environment :: X11 Applications
Classifier: Environment :: Console :: Framebuffer
Classifier: Intended Audience :: End Users/Desktop
Classifier: License :: OSI Approved :: GNU Library or Lesser General Public License (LGPL)
Classifier: Operating System :: POSIX
Classifier: Programming Language :: C
Classifier: Programming Language :: Cython
Classifier: Programming Language :: Python :: 2
Classifier: Programming Language :: Python :: 3
Classifier: Topic :: Software Development :: Libraries :: Python Modules
Classifier: Topic :: Software Development :: User Interfaces
Classifier: Topic :: Software Development :: Widget Sets
License-File: COPYING
License-File: COPYING.LESSER
License-File: AUTHORS
